maslow/__init__.py
maslow/admin.py
maslow/apps.py
maslow/models.py
maslow/urls.py
maslow/views.py
maslow/migrations/__init__.py
maslow/templates/admin_template.html
maslow/templatetags/.DS_Store
maslow/templatetags/basics.py
maslow/templatetags/__pycache__/basics.cpython-35.pyc
maslow/templatetags/__pycache__/basics.cpython-36.pyc
maslow/templatetags/__pycache__/basics.cpython-37.pyc
django_maslow-0.7.0.dist-info/LICENSE
django_maslow-0.7.0.dist-info/METADATA
django_maslow-0.7.0.dist-info/WHEEL
django_maslow-0.7.0.dist-info/top_level.txt
django_maslow-0.7.0.dist-info/RECORD
