Metadata-Version: 2.1
Name: django-maslow
Version: 0.7.0
Summary: A simple Django base app.
Home-page: http://www.obitec.co.za/
Author: JR Minnaar
Author-email: jr.minnaar+pypi@gmail.com
License: MIT License
Platform: UNKNOWN
Classifier: Environment :: Web Environment
Classifier: Framework :: Django
Classifier: Intended Audience :: Developers
Classifier: License :: OSI Approved :: BSD License
Classifier: Operating System :: OS Independent
Classifier: Programming Language :: Python
Classifier: Programming Language :: Python :: 3
Classifier: Topic :: Internet :: WWW/HTTP
Classifier: Topic :: Internet :: WWW/HTTP :: Dynamic Content
